newtonpa.cp312-win_amd64.pyd
newtonpa-2.2.0.dist-info/METADATA
newtonpa-2.2.0.dist-info/WHEEL
newtonpa-2.2.0.dist-info/top_level.txt
newtonpa-2.2.0.dist-info/RECORD
