Metadata-Version: 2.1
Name: newtonpa
Version: 2.2.0
Summary: Newton, A high-efficiency power systems solver
Home-page: https://www.advancedgridinsights.com/newton
Author: Santiago Peñate Vera
Author-email: santiago.penate@redeia.com
Keywords: power systems planning
Classifier: Programming Language :: Python :: 3.6
Classifier: Programming Language :: Python :: 3.7
Classifier: Programming Language :: Python :: 3.8
Classifier: Programming Language :: Python :: 3.9
Requires-Dist: numpy
Requires-Dist: scipy
